ConceptModelling/__init__.py
ConceptModelling/text_preprocessing.py
ConceptModelling/thumbs_up_down.py
ConceptModelling/data/ar.affective.words.json
ConceptModelling/data/en.affective.words.json
ConceptModelling/data/es.affective.words.json
ConceptModelling/tests/test_thumbs_up_down.py
ConceptModelling-0.1.2.dist-info/LICENSE
ConceptModelling-0.1.2.dist-info/METADATA
ConceptModelling-0.1.2.dist-info/WHEEL
ConceptModelling-0.1.2.dist-info/top_level.txt
ConceptModelling-0.1.2.dist-info/RECORD
