Metadata-Version: 2.1
Name: ConceptModelling
Version: 0.1.2
Summary: ConceptModelling
Home-page: https://github.com/ingeotec/ConceptModelling
Author: Sabino Miranda Jimenez
Author-email: mgraffg@ieee.org
License: UNKNOWN
Platform: UNKNOWN
Classifier: Development Status :: 3 - Alpha
Classifier: Environment :: Console
Classifier: Intended Audience :: Science/Research
Classifier: License :: OSI Approved :: Apache Software License
Classifier: Natural Language :: English
Classifier: Operating System :: MacOS :: MacOS X
Classifier: Operating System :: POSIX :: Linux
Classifier: Programming Language :: Python :: 3
Classifier: Topic :: Scientific/Engineering :: Artificial Intelligence
